hello_auz/__init__.py
hello_auz/hello.py
hello_auz-0.1.dist-info/METADATA
hello_auz-0.1.dist-info/WHEEL
hello_auz-0.1.dist-info/top_level.txt
hello_auz-0.1.dist-info/RECORD
